driver_manager/__init__.py
driver_manager-0.1.1.dist-info/METADATA
driver_manager-0.1.1.dist-info/WHEEL
driver_manager-0.1.1.dist-info/top_level.txt
driver_manager-0.1.1.dist-info/RECORD
