Metadata-Version: 2.4
Name: driver-manager
Version: 0.1.1
Summary: A lightweight ChromeDriver version fetcher for Python
Author-email: Roshan Jha <roshanjha88262@gmail.com>
License: MIT
Project-URL: Homepage, https://github.com/roshankrjha/driver-manager
Requires-Python: >=3.7
Requires-Dist: requests
